py_ha_smn-1.0.0.dist-info/licenses/LICENSE
smn_argentina_api/__init__.py
smn_argentina_api/client.py
smn_argentina_api/const.py
smn_argentina_api/exceptions.py
smn_argentina_api/py.typed
py_ha_smn-1.0.0.dist-info/METADATA
py_ha_smn-1.0.0.dist-info/WHEEL
py_ha_smn-1.0.0.dist-info/top_level.txt
py_ha_smn-1.0.0.dist-info/RECORD
