Metadata-Version: 2.4
Name: py-ha-smn
Version: 1.0.0
Summary: Async Python client for the Servicio Meteorológico Nacional Argentina (SMN) API
Author-email: catastrophicode <catastrophicode@users.noreply.github.com>
License: Apache-2.0
Project-URL: Homepage, https://github.com/catastrophicode/py-ha-smn
Project-URL: Repository, https://github.com/catastrophicode/py-ha-smn
Project-URL: Issues, https://github.com/catastrophicode/py-ha-smn/issues
Keywords: smn,argentina,weather,api,async,aiohttp,home-assistant
Classifier: Development Status :: 4 - Beta
Classifier: Intended Audience :: Developers
Classifier: License :: OSI Approved :: Apache Software License
Classifier: Operating System :: OS Independent
Classifier: Programming Language :: Python :: 3
Classifier: Programming Language :: Python :: 3.11
Classifier: Programming Language :: Python :: 3.12
Classifier: Programming Language :: Python :: 3.13
Classifier: Topic :: Software Development :: Libraries :: Python Modules
Classifier: Topic :: Scientific/Engineering :: Atmospheric Science
Requires-Python: >=3.11
License-File: LICENSE
Requires-Dist: aiohttp>=3.8.0
Provides-Extra: dev
Requires-Dist: pytest>=7.0.0; extra == "dev"
Requires-Dist: pytest-asyncio>=0.21.0; extra == "dev"
Requires-Dist: pytest-cov>=4.0.0; extra == "dev"
Requires-Dist: aioresponses>=0.7.4; extra == "dev"
Requires-Dist: ruff>=0.1.0; extra == "dev"
Requires-Dist: mypy>=1.0.0; extra == "dev"
Dynamic: license-file
